Rammbock/__init__.py
Rammbock/binary_tools.py
Rammbock/condition_parser.py
Rammbock/core.py
Rammbock/decorator.py
Rammbock/logger.py
Rammbock/message.py
Rammbock/message_sequence.py
Rammbock/networking.py
Rammbock/ordered_dict.py
Rammbock/rammbock.py
Rammbock/robotbackgroundlogger.py
Rammbock/synchronization.py
Rammbock/version.py
Rammbock/templates/__init__.py
Rammbock/templates/containers.py
Rammbock/templates/message_stream.py
Rammbock/templates/primitives.py
robotframework_rammbock_py3-0.4.0.2.dist-info/LICENSE.txt
robotframework_rammbock_py3-0.4.0.2.dist-info/METADATA
robotframework_rammbock_py3-0.4.0.2.dist-info/WHEEL
robotframework_rammbock_py3-0.4.0.2.dist-info/top_level.txt
robotframework_rammbock_py3-0.4.0.2.dist-info/RECORD
