Metadata-Version: 2.1
Name: robotframework-rammbock-py3
Version: 0.4.0.2
Summary: Protocol testing library for Robot Framework
Home-page: http://github.com/robotframework/Rammbock/
Author: Robot Framework Developers
Author-email: robotframework-users@googlegroups.com
License: UNKNOWN
Platform: UNKNOWN
